{
    "type": "FeatureCollection",
    "features": [
     
        {
            "type": "Feature",
            "properties": {
                "location": "Sklad ucheta 1",
                "discipline": "Sklad",
                "title": "Sklad Ucheta N1",
            },
            "geometry": {
                "type": "Point",
                "coordinates": [
                    60.6150221408886,
                    56.83619945712329
                ]
            }
        },
        {
            "type": "Feature",
            "properties": {
                "location": "Sklad ucheta 2",
                "discipline": "Sklad",
                "title": "Sklad Ucheta N2",
            },
            "geometry": {
                "type": "Point",
                "coordinates": [
                    60.604713023768696,
                    56.845369941777726
                ]
            }
        },
        
        
        
    ]
}
